LICENSE
MANIFEST.in
README.md
quicktest.py
settings_test.py
setup.py
django_vkontakte_wall.egg-info/PKG-INFO
django_vkontakte_wall.egg-info/SOURCES.txt
django_vkontakte_wall.egg-info/dependency_links.txt
django_vkontakte_wall.egg-info/not-zip-safe
django_vkontakte_wall.egg-info/requires.txt
django_vkontakte_wall.egg-info/top_level.txt
vkontakte_wall/__init__.py
vkontakte_wall/__init__.pyc
vkontakte_wall/admin.py
vkontakte_wall/admin.pyc
vkontakte_wall/factories.py
vkontakte_wall/factories.pyc
vkontakte_wall/mixins.py
vkontakte_wall/mixins.pyc
vkontakte_wall/models.py
vkontakte_wall/models.pyc
vkontakte_wall/parser.py
vkontakte_wall/parser.pyc
vkontakte_wall/tests.py
vkontakte_wall/tests.pyc
vkontakte_wall/migrations/0001_initial.py
vkontakte_wall/migrations/0001_initial.pyc
vkontakte_wall/migrations/0002_auto__del_field_comment_reply_to_uid__del_field_comment_reply_to_cid__.py
vkontakte_wall/migrations/0002_auto__del_field_comment_reply_to_uid__del_field_comment_reply_to_cid__.pyc
vkontakte_wall/migrations/0003_auto__del_field_comment_reply_for__del_field_comment_user__add_field_c.py
vkontakte_wall/migrations/0003_auto__del_field_comment_reply_for__del_field_comment_user__add_field_c.pyc
vkontakte_wall/migrations/0004_auto__add_field_comment_raw_html__add_field_post_raw_html.py
vkontakte_wall/migrations/0004_auto__add_field_comment_raw_html__add_field_post_raw_html.pyc
vkontakte_wall/migrations/0005_auto__add_field_comment_wall_owner_content_type__add_field_comment_wal.py
vkontakte_wall/migrations/0005_auto__add_field_comment_wall_owner_content_type__add_field_comment_wal.pyc
vkontakte_wall/migrations/0006_auto.py
vkontakte_wall/migrations/0006_auto.pyc
vkontakte_wall/migrations/0007_auto__del_field_post_copy_post_id__add_field_post_copy_owner_content_t.py
vkontakte_wall/migrations/0007_auto__del_field_post_copy_post_id__add_field_post_copy_owner_content_t.pyc
vkontakte_wall/migrations/0008_auto__add_field_comment_raw_json__add_field_post_raw_json__chg_field_p.py
vkontakte_wall/migrations/0008_auto__add_field_comment_raw_json__add_field_post_raw_json__chg_field_p.pyc
vkontakte_wall/migrations/0009_auto.py
vkontakte_wall/migrations/0009_auto.pyc
vkontakte_wall/migrations/0010_auto.py
vkontakte_wall/migrations/0010_auto.pyc
